videorotation/__init__.py
videorotation/birotnet.py
videorotation/check_upsidedown.py
videorotation/mobilenet2_bi-rotnet.tflite
videorotation-0.2.3.dist-info/METADATA
videorotation-0.2.3.dist-info/WHEEL
videorotation-0.2.3.dist-info/top_level.txt
videorotation-0.2.3.dist-info/RECORD
