Metadata-Version: 2.1
Name: videorotation
Version: 0.2.3
Summary: A module that allows to estimate whether video is flipped
Home-page: https://github.com/pavloshargan/VideoRotationAnalysis
Author: Pavlo Sharhan
Author-email: activetechinnovators@example.com
Requires-Dist: opencv-python
Requires-Dist: numpy
Requires-Dist: tensorflow
